{
  "kind": "coverage_report",
  "version": "1.0",
  "generatedAt": "2026-02-10T20:21:41.616Z",
  "sources": {
    "buildRequest": true,
    "implementationPlan": true
  },
  "requirements": {
    "total": 2,
    "implemented": 2,
    "items": [
      {
        "id": "REQ-5",
        "summary": "Update the Dashboard page (frontend/src/pages/Dashboard.tsx) to render a new section titled \"Alerts\" directly below the existing \"Recent Activity\" section, using the same spacing and card styling patterns as the rest of the Dashboard.",
        "status": "implemented",
        "plannedFiles": [
          "frontend/src/pages/Dashboard.tsx"
        ],
        "matchedFiles": [
          "frontend/src/pages/Dashboard.tsx"
        ]
      },
      {
        "id": "REQ-6",
        "summary": "In the new Dashboard \"Alerts\" section, compute and display alert items as follows: (1) If there are any territories that are currently checked out and have been checked out for 4 months or more, display a red alert box with the text \"X territories overdue for return\" and a link that navigates to the Territories page. (2) If there are any tasks where dueDate is in the past and isCompleted is false, display an orange alert box with the text \"X overdue tasks\" and a link that navigates to the Tasks page. (3) If neither condition is present, display muted gray text \"No alerts\".",
        "status": "implemented",
        "plannedFiles": [
          "frontend/src/pages/Dashboard.tsx"
        ],
        "matchedFiles": [
          "frontend/src/pages/Dashboard.tsx"
        ]
      }
    ]
  },
  "changedFiles": [
    "build-request.json",
    "feature_evidence.json",
    "frontend-file-summaries.txt",
    "frontend-implementation-plan.json",
    "frontend/src/pages/Dashboard.tsx",
    "project_state.json",
    "scratch/component-selection.json",
    "spec.md",
    "spec_vs_diff_report.json"
  ]
}